chatgpt_voice_assistant/__init__.py
chatgpt_voice_assistant/bases/__init__.py
chatgpt_voice_assistant/bases/listener.py
chatgpt_voice_assistant/bases/options_parser.py
chatgpt_voice_assistant/bases/responder.py
chatgpt_voice_assistant/bases/text_generator.py
chatgpt_voice_assistant/bases/text_to_speech_client.py
chatgpt_voice_assistant/cli_parser.py
chatgpt_voice_assistant/clients/__init__.py
chatgpt_voice_assistant/clients/apple_say_text_to_speech_client.py
chatgpt_voice_assistant/clients/google_text_to_speech_client.py
chatgpt_voice_assistant/clients/open_ai_client.py
chatgpt_voice_assistant/clients/openai_text_to_speech_client.py
chatgpt_voice_assistant/computer_voice_responder.py
chatgpt_voice_assistant/conversation.py
chatgpt_voice_assistant/exceptions/__init__.py
chatgpt_voice_assistant/exceptions/failed_to_understand_listener_error.py
chatgpt_voice_assistant/exceptions/invalid_input_device_index_error.py
chatgpt_voice_assistant/exceptions/listener_error.py
chatgpt_voice_assistant/exceptions/listener_fatal_error.py
chatgpt_voice_assistant/exceptions/no_input_devices_found_error.py
chatgpt_voice_assistant/exceptions/no_input_listener_error.py
chatgpt_voice_assistant/exceptions/respond_error.py
chatgpt_voice_assistant/exceptions/text_generation_error.py
chatgpt_voice_assistant/helpers/__init__.py
chatgpt_voice_assistant/helpers/get_input_device_from_user.py
chatgpt_voice_assistant/helpers/set_keyboard_interrupt_handler.py
chatgpt_voice_assistant/helpers/set_log_level.py
chatgpt_voice_assistant/input_devices.py
chatgpt_voice_assistant/main.py
chatgpt_voice_assistant/models/__init__.py
chatgpt_voice_assistant/models/command_line_arguments.py
chatgpt_voice_assistant/models/input_device.py
chatgpt_voice_assistant/models/message.py
chatgpt_voice_assistant/models/open_ai_chat_completion.py
chatgpt_voice_assistant/models/pyaudio_device_info.py
chatgpt_voice_assistant/open_ai_text_generator.py
chatgpt_voice_assistant/py.typed
chatgpt_voice_assistant/speech_listener.py
chatgpt_voice_assistant-2.0.1.dist-info/METADATA
chatgpt_voice_assistant-2.0.1.dist-info/WHEEL
chatgpt_voice_assistant-2.0.1.dist-info/entry_points.txt
chatgpt_voice_assistant-2.0.1.dist-info/RECORD
