Metadata-Version: 2.1
Name: chatgpt_voice_assistant
Version: 2.0.1
Summary: Package to speak with OpenAI's GPT models
Author: Jake Cyr
Author-email: cyrjake@gmail.com
Requires-Python: >=3.9,<4.0
Classifier: Programming Language :: Python :: 3
Classifier: Programming Language :: Python :: 3.9
Classifier: Programming Language :: Python :: 3.10
Classifier: Programming Language :: Python :: 3.11
Classifier: Programming Language :: Python :: 3.12
Requires-Dist: gtts (>=2.3.1,<3.0)
Requires-Dist: openai (>=1.30.2,<2.0.0)
Requires-Dist: pyaudio (>=0.2.13,<0.3)
Requires-Dist: speechrecognition (==3.10.1)
